kcpp/__init__.py
kcpp/cc/__init__.py
kcpp/cc/frontend.py
kcpp/core/__init__.py
kcpp/core/host.py
kcpp/core/target.py
kcpp/core/targets.py
kcpp/core/types.py
kcpp/cpp/__init__.py
kcpp/cpp/expressions.py
kcpp/cpp/file_manager.py
kcpp/cpp/lexer.py
kcpp/cpp/literals.py
kcpp/cpp/locator.py
kcpp/cpp/macros.py
kcpp/cpp/preprocessor.py
kcpp/cpp/tests/test_lexer.py
kcpp/diagnostics/__init__.py
kcpp/diagnostics/definitions.py
kcpp/diagnostics/diagnostic.py
kcpp/diagnostics/terminal.py
kcpp/driver/__init__.py
kcpp/driver/driver.py
kcpp/driver/frontends.py
kcpp/driver/skins.py
kcpp/parsing/__init__.py
kcpp/parsing/state.py
kcpp/unicode/__init__.py
kcpp/unicode/char_ranges.py
kcpp/unicode/charset.py
kcpp/unicode/cp_name_db.py
kcpp/unicode/name_to_cp.py
kcpp/unicode/nf_tables.py
kcpp/unicode/tests/test_name_to_cp.py
kcpp/unicode/tests/test_nf.py
kcpp/unicode/tests/test_utf8.py
kcpp-0.7.dist-info/licenses/LICENCE
kcpp-0.7.dist-info/METADATA
kcpp-0.7.dist-info/WHEEL
kcpp-0.7.dist-info/entry_points.txt
kcpp-0.7.dist-info/top_level.txt
kcpp-0.7.dist-info/RECORD
