Metadata-Version: 2.4
Name: kcpp
Version: 0.7
Summary: A preprocessor for C++23 writen in Python, implemented as a library
Download-URL: https://github.com/kyuupichan/kcpp/archive/{version}.tar.gz
Author-email: Neil Booth <kyuupichan@pm.me>
Maintainer-email: Neil Booth <kyuupichan@pm.me>
Project-URL: Project-URL, https://github.com/kyuupichan/kcpp
Keywords: preprocessor,C++,C
Classifier: Development Status :: 2 - Pre-Alpha
Classifier: Intended Audience :: Developers
Classifier: License :: OSI Approved :: MIT License
Classifier: Operating System :: OS Independent
Classifier: Programming Language :: Python :: 3.10
Classifier: Environment :: Console
Classifier: Topic :: Software Development :: Compilers
Classifier: Topic :: Software Development :: Libraries :: Python Modules
Requires-Python: >=3.10
License-File: LICENCE
Dynamic: download-url
Dynamic: license-file
